<?xml version="1.0" encoding="UTF-8"?>
<GenRun Id="videoClk108MHz_synth_1" LaunchPart="xc7a100tcsg324-1" LaunchTime="1553636527">
  <File Type="PA-TCL" Name="videoClk108MHz.tcl"/>
  <File Type="RDS-PROPCONSTRS" Name="videoClk108MHz_drc_synth.rpt"/>
  <File Type="REPORTS-TCL" Name="videoClk108MHz_reports.tcl"/>
  <File Type="RDS-RDS" Name="videoClk108MHz.vds"/>
  <File Type="RDS-UTIL" Name="videoClk108MHz_utilization_synth.rpt"/>
  <File Type="RDS-UTIL-PB" Name="videoClk108MHz_utilization_synth.pb"/>
  <File Type="RDS-DCP" Name="videoClk108MHz.dcp"/>
  <File Type="VDS-TIMINGSUMMARY" Name="videoClk108MHz_timing_summary_synth.rpt"/>
  <File Type="VDS-TIMING-PB" Name="videoClk108MHz_timing_summary_synth.pb"/>
  <FileSet Name="sources" Type="BlockSrcs" RelSrcDir="$PSRCDIR/videoClk108MHz">
    <File Path="$PSRCDIR/sources_1/ip/videoClk108MHz/videoClk108MHz.xci">
      <FileInfo>
        <Attr Name="UsedIn" Val="synthesis"/>
        <Attr Name="UsedIn" Val="implementation"/>
        <Attr Name="UsedIn" Val="simulation"/>
      </FileInfo>
    </File>
    <Config>
      <Option Name="TopModule" Val="videoClk108MHz"/>
      <Option Name="UseBlackboxStub" Val="1"/>
    </Config>
  </FileSet>
  <FileSet Name="constrs_in" Type="BlockSrcs" RelSrcDir="$PSRCDIR/videoClk108MHz">
    <File Path="$PSRCDIR/sources_1/ip/videoClk108MHz/videoClk108MHz.xci">
      <FileInfo>
        <Attr Name="UsedIn" Val="synthesis"/>
        <Attr Name="UsedIn" Val="implementation"/>
        <Attr Name="UsedIn" Val="simulation"/>
      </FileInfo>
    </File>
    <Config>
      <Option Name="TopModule" Val="videoClk108MHz"/>
      <Option Name="UseBlackboxStub" Val="1"/>
    </Config>
  </FileSet>
  <FileSet Name="utils" Type="Utils" RelSrcDir="$PSRCDIR/utils_1">
    <Filter Type="Utils"/>
    <Config>
      <Option Name="TopAutoSet" Val="TRUE"/>
    </Config>
  </FileSet>
  <Strategy Version="1" Minor="2">
    <StratHandle Name="Vivado Synthesis Defaults" Flow="Vivado Synthesis 2018">
      <Desc>Vivado Synthesis Defaults</Desc>
    </StratHandle>
    <Step Id="synth_design"/>
  </Strategy>
</GenRun>
